mfg/__init__.py
mfg/mfg.py
mfg-1.0.0.dist-info/LICENSE
mfg-1.0.0.dist-info/METADATA
mfg-1.0.0.dist-info/WHEEL
mfg-1.0.0.dist-info/top_level.txt
mfg-1.0.0.dist-info/RECORD
