Metadata-Version: 2.1
Name: mfg
Version: 1.0.0
Summary: Display a message on foreground
Home-page: https://github.com/Game-K-Hack/Message-Foreground
Author: Game K
Author-email: game_k@laposte.net
License: UNKNOWN
Project-URL: Bug Tracker, https://github.com/Game-K-Hack/Message-Foreground/issues
Platform: UNKNOWN
Classifier: Programming Language :: Python :: 3
Classifier: License :: OSI Approved :: MIT License
Classifier: Operating System :: OS Independent
Requires-Python: >=3.6
License-File: LICENSE
